setup.cfg
setup.py
unplag/__init__.py
unplag/check.py
unplag/connection.py
unplag/directory.py
unplag/file.py
unplag/response.py
unplag/unplag.py
unplag.egg-info/PKG-INFO
unplag.egg-info/SOURCES.txt
unplag.egg-info/dependency_links.txt
unplag.egg-info/not-zip-safe
unplag.egg-info/requires.txt
unplag.egg-info/top_level.txt