Metadata-Version: 1.0
Name: unplag
Version: 1.0.6
Summary: Unplag API python client
Home-page: https://unplag.com
Author: Oleg Mykolaichenko
Author-email: mukolaichenko@gmail.com
License: Apache 2.0 License
Platform: UNKNOWN
